nonebot_plugin_fupan/__init__.py
nonebot_plugin_fupan/config.py
nonebot_plugin_fupan-0.1.8.dist-info/WHEEL
nonebot_plugin_fupan-0.1.8.dist-info/METADATA
nonebot_plugin_fupan-0.1.8.dist-info/RECORD
