Metadata-Version: 2.3
Name: nonebot-plugin-fupan
Version: 0.1.8
Summary: NoneBot 复盘打卡插件，用于帮助交易者进行每日复盘打卡。支持交易日判断、时间窗口控制、数据统计等功能。
Author: zanderzhng
Author-email: zanderzhng <zanderzhng@gmail.com>
Requires-Dist: nonebot2>=2.4.3,<3.0.0
Requires-Dist: nonebot-plugin-localstore>=0.7.4,<1.0.0
Requires-Dist: nonebot-plugin-apscheduler>=0.5.0,<1.0.0
Requires-Dist: nonebot-plugin-uninfo>=0.9.0,<1.0.0
Requires-Dist: httpx>=0.27.0,<1.0.0
Requires-Dist: exchange-calendars>=4.11.1
Requires-Python: >=3.10
Project-URL: Repository, https://github.com/zanderzhng/nonebot-plugin-fupan
